omega_match/__init__.py
omega_match/_cffi_stub.pyi
omega_match/omega_match.py
omega_match/py.typed
omega_match/native/lib/.keep
omega_match/native/lib/libomega_match-linux-arm64.so
omega_match/native/lib/libomega_match-linux-x64-clang-pgo.so
omega_match/native/lib/libomega_match-linux-x64-gcc-pgo.so
omega_match/native/lib/libomega_match-linux-x64.so
omega_match/native/lib/libomega_match-macos-arm64.dylib
omega_match/native/lib/libomega_match-windows-x64-msvc-pgo.dll
omega_match/native/lib/libomega_match-windows-x64.dll
omega_match-0.2.1.dist-info/licenses/LICENSE
tests/test_omega_match.py
omega_match-0.2.1.dist-info/METADATA
omega_match-0.2.1.dist-info/WHEEL
omega_match-0.2.1.dist-info/top_level.txt
omega_match-0.2.1.dist-info/RECORD
