Metadata-Version: 2.4
Name: omega_match
Version: 0.2.1
Summary: High-performance multi-string matcher with native C backend
Home-page: https://github.com/scholarsmate/omega-match
Author: Davin Shearer
Author-email: scholarsmate@gmail.com
License: Apache 2.0
Classifier: Programming Language :: Python :: 3.9
Classifier: Programming Language :: Python :: 3.10
Classifier: Programming Language :: Python :: 3.11
Classifier: Programming Language :: Python :: 3.12
Classifier: Programming Language :: Python :: 3.13
Requires-Python: >=3.9
License-File: LICENSE
Requires-Dist: argcomplete>=3.6.2
Requires-Dist: cffi>=1.15.1
Dynamic: classifier
Dynamic: license-file
Dynamic: requires-python
